auto_function_serving/ServerHandler.py
auto_function_serving/__init__.py
auto_function_serving-0.1.3.dist-info/LICENSE
auto_function_serving-0.1.3.dist-info/METADATA
auto_function_serving-0.1.3.dist-info/WHEEL
auto_function_serving-0.1.3.dist-info/top_level.txt
auto_function_serving-0.1.3.dist-info/RECORD
