Metadata-Version: 2.1
Name: auto-function-serving
Version: 0.1.3
Summary: A python package to offload a function call to an http server automatically using a decorator.
Author-email: Arrman Anicket Saha <arrmansa99+430@gmail.com>
Project-URL: Homepage, https://github.com/arrmansa/auto-function-serving
Project-URL: Bug Tracker, https://github.com/arrmansa/auto-function-serving/issues
Classifier: Programming Language :: Python :: 3
Classifier: License :: OSI Approved :: Apache Software License
Classifier: Operating System :: OS Independent
Requires-Python: >=3.7
License-File: LICENSE
Requires-Dist: aiohttp (>=3.7.2)
